setup.py
gaussian_binomial_distributions_trohl/Binomialdistribution.py
gaussian_binomial_distributions_trohl/Gaussiandistribution.py
gaussian_binomial_distributions_trohl/Generaldistribution.py
gaussian_binomial_distributions_trohl/__init__.py
gaussian_binomial_distributions_trohl.egg-info/PKG-INFO
gaussian_binomial_distributions_trohl.egg-info/SOURCES.txt
gaussian_binomial_distributions_trohl.egg-info/dependency_links.txt
gaussian_binomial_distributions_trohl.egg-info/not-zip-safe
gaussian_binomial_distributions_trohl.egg-info/top_level.txt