Metadata-Version: 1.0
Name: gaussian-binomial-distributions-trohl
Version: 0.1
Summary: Gaussian and binomial distributions
Home-page: UNKNOWN
Author: Thorsten Rohling
Author-email: thorstenrohling@aol.com
License: UNKNOWN
Platform: UNKNOWN
